{
	"10":
	{
		"Working": true
	},
	"20":
	{
		"Working": true
	},
	"30":
	{
		"Working": true
	},
	"40":
	{
		"Working": true
	},
	"50":
	{
		"Working": true
	},
	"60":
	{
		"Working": true
	},
	"70":
	{
		"Working": true
	},
	"80":
	{
		"Working": true
	},
	"100":
	{
		"Working": true
	},
	"130":
	{
		"Working": true
	},
	"220":
	{
		"Working": true
	},
	"240":
	{
		"Working": true
	},
	"280":
	{
		"Working": true
	},
	"300":
	{
		"Working": true
	},
	"320":
	{
		"Working": true
	},
	"340":
	{
		"Working": true
	},
	"360":
	{
		"Working": true
	},
	"380":
	{
		"Working": true
	},
	"400":
	{
		"Working": true
	},
	"420":
	{
		"Working": true
	},
	"440":
	{
		"Working": true
	},
	"550":
	{
		"Working": true
	},
	"570":
	{
		"Working": true
	},
	"580":
	{
		"Hidden": true,
		"Comment": "Server, not a game."
	},
	"620":
	{
		"Working": true,
		"Beta": true
	},
	"742":
	{
		"Hidden": true,
		"Comment": "Server, not a game."
	},
	"790":
	{
		"Hidden": true,
		"Comment": "Server, not a game."
	},
	"817":
	{
		"Hidden": true,
		"Comment": "Server, not a game."
	},
	"1007":
	{
		"Hidden": true,
		"Comment": "Steamworks SDK Redist"
	},
	"1200":
	{
		"Working": true
	},
	"1230":
	{
		"Working": true
	},
	"1250":
	{
		"Working": true
	},
	"1280":
	{
		"Working": true
	},
	"1500":
	{
		"Working": true
	},
	"1510":
	{
		"Working": true
	},
	"1520":
	{
		"Working": true
	},
	"1530":
	{
		"Working": true
	},
	"2810":
	{
		"Working": true
	},
	"2820":
	{
		"Working": true
	},
	"3830":
	{
		"Working": true
	},
	"4000":
	{
		"Working": true
	},
	"4920":
	{
		"Working": true
	},
	"6120":
	{
		"Working": true
	},
	"13700":
	{
		"Working": true,
		"Comment": "Broken overlay."
	},
	"15400":
	{
		"Working": true
	},
	"15560":
	{
		"Working": true
	},
	"17520":
	{
		"Working": true
	},
	"17590":
	{
		"Hidden": true,
		"Comment": "Dystopia Beta"
	},
	"17710":
	{
		"Working": true
	},
	"18300":
	{
		"Working": true
	},
	"18700":
	{
		"Working": true
	},
	"20820":
	{
		"Working": true
	},
	"20920":
	{
		"Working": true
	},
	"22000":
	{
		"Working": true
	},
	"22120":
	{
		"Working": true
	},
	"22140":
	{
		"Working": true
	},
	"22180":
	{
		"Working": true
	},
	"22600":
	{
		"Working": true
	},
	"24420":
	{
		"Working": true
	},
	"25000":
	{
		"Working": true
	},
	"25010":
	{
		"Working": true
	},
	"25600":
	{
		"Working": true
	},
	"25620":
	{
		"Working": true
	},
	"26500":
	{
		"Working": true
	},
	"29160":
	{
		"Working": true
	},
	"29180":
	{
		"Working": true
	},
	"33600":
	{
		"Working": true
	},
	"33680":
	{
		"Working": true
	},
	"35480":
	{
		"Working": true
	},
	"35720":
	{
		"Working": true
	},
	"38600":
	{
		"Working": true,
		"Beta": true
	},
	"38700":
	{
		"Working": true
	},
	"38720":
	{
		"Working": true
	},
	"38740":
	{
		"Working": true
	},
	"40800":
	{
		"Working": true
	},
	"41070":
	{
		"Working": true
	},
	"41100":
	{
		"Working": true
	},
	"41300":
	{
		"Working": true
	},
	"41800":
	{
		"Working": true
	},
	"41900":
	{
		"Working": true
	},
	"43160":
	{
		"Working": true
	},
	"44200":
	{
		"Working": true
	},
	"45100":
	{
		"Working": true
	},
	"45450":
	{
		"Working": true
	},
	"45900":
	{
		"Working": true,
		"Comment": "A Wine Bottle."
	},
	"49600":
	{
		"Working": true
	},
	"57300":
	{
		"Working": true
	},
	"57640":
	{
		"Working": true,
		"Comment": "Ignores SDL environment variables so isn't playable on multiple displays."
	},
	"57740":
	{
		"Working": true
	},
	"58610":
	{
		"Working": true
	},
	"61600":
	{
		"Working": true
	},
	"63000":
	{
		"Working": true
	},
	"65800":
	{
		"Working": true
	},
	"67000":
	{
		"Working": true
	},
	"70100":
	{
		"Working": true
	},
	"70120":
	{
		"Working": true
	},
	"70300":
	{
		"Working": true
	},
	"72000":
	{
		"Working": true
	},
	"73010":
	{
		"Working": true
	},
	"73080":
	{
		"Hidden": true,
		"Comment": "Crusader Kings 2 Beta"
	},
	"80310":
	{
		"Working": true
	},
	"91200":
	{
		"Working": true
	},
	"92800":
	{
		"Working": true
	},
	"93200":
	{
		"Working": true
	},
	"95000":
	{
		"Working": true
	},
	"95300":
	{
		"Working": true
	},
	"96200":
	{
		"Working": true
	},
	"97000":
	{
		"Working": true
	},
	"98200":
	{
		"Working": true
	},
	"98800":
	{
		"Working": true,
		"Comment": "Broken overlay."
	},
	"102840":
	{
		"Working": true
	},
	"105100":
	{
		"Working": true,
		"Comment": "Overlay works only in full-screen mode. Steamworks features are unavailable."
	},
	"107100":
	{
		"Working": true
	},
	"107200":
	{
		"Working": true
	},
	"107800":
	{
		"Working": true
	},
	"108200":
	{
		"Working": true
	},
	"108600":
	{
		"Working": true
	},
	"111000":
	{
		"Working": true,
		"Comment": "Broken overlay."
	},
	"111010":
	{
		"Working": true,
		"Comment": "Broken overlay."
	},
	"111100":
	{
		"Working": true
	},
	"111700":
	{
		"Hidden": true,
		"Comment": "Nuclear Dawn Staging"
	},
	"111800":
	{
		"Working": true
	},
	"112100":
	{
		"Working": true
	},
	"113020":
	{
		"Working": true
	},
	"115100":
	{
		"Working": true
	},
	"115110":
	{
		"Working": true
	},
	"200390":
	{
		"Working": true
	},
	"200900":
	{
		"Working": true
	},
	"201040":
	{
		"Working": true
	},
	"201310":
	{
		"Working": true
	},
	"201420":
	{
		"Working": true
	},
	"202730":
	{
		"Working": true
	},
	"203210":
	{
		"Working": true
	},
	"203770":
	{
		"Working": true
	},
	"204060":
	{
		"Working": true
	},
	"204180":
	{
		"Working": true
	},
	"204220":
	{
		"Working": true
	},
	"204240":
	{
		"Working": true
	},
	"204300":
	{
		"Working": true
	},
	"205790":
	{
		"Working": true
	},
	"205800":
	{
		"Hidden": true,
		"Comment": "Server, not a game."
	},
	"205910":
	{
		"Working": true
	},
	"206440":
	{
		"Working": true
	},
	"206690":
	{
		"Working": true
	},
	"207080":
	{
		"Working": true,
		"Beta": true
	},
	"207170":
	{
		"Working": true
	},
	"207250":
	{
		"Working": true
	},
	"207570":
	{
		"Working": true
	},
	"207650":
	{
		"Working": true
	},
	"207750":
	{
		"Working": true
	},
	"209080":
	{
		"Working": true
	},
	"209190":
	{
		"Working": true
	},
	"209270":
	{
		"Working": true
	},
	"209370":
	{
		"Working": true
	},
	"209540":
	{
		"Working": true
	},
	"209790":
	{
		"Working": true,
		"Comment": "Achievements do not unlock.",
		"CommentURL": "http://steamcommunity.com/app/209790/discussions/0/864951657745931480/#c828925216497607741"
	},
	"210170":
	{
		"Working": true
	},
	"210770":
	{
		"Working": true,
		"Beta": true
	},
	"211340":
	{
		"Working": true,
		"Comment": "Broken overlay."
	},
	"211820":
	{
		"Working": true
	},
	"211900":
	{
		"Working": true
	},
	"212070":
	{
		"Working": true
	},
	"212680":
	{
		"Working": true
	},
	"213650":
	{
		"Working": true
	},
	"214420":
	{
		"Working": true,
		"Comment": "Broken overlay."
	},
	"214550":
	{
		"Working": true
	},
	"214560":
	{
		"Working": true
	},
	"214770":
	{
		"Working": true
	},
	"214870":
	{
		"Working": true
	},
	"214910":
	{
		"Working": true
	},
	"214970":
	{
		"Working": true,
		"Comment": "Broken overlay. Steamworks features are unavailable."
	},
	"215160":
	{
		"Working": true,
		"Comment": "Broken overlay."
	},
	"215360":
	{
		"Hidden": true,
		"Comment": "Server, not a game."
	},
	"215510":
	{
		"Working": true
	},
	"216290":
	{
		"Working": true
	},
	"217690":
	{
		"Working": true
	},
	"218060":
	{
		"Working": true
	},
	"218090":
	{
		"Working": true
	},
	"218410":
	{
		"Working": true,
		"Comment": "Broken overlay."
	},
	"218660":
	{
		"Working": true
	},
	"219150":
	{
		"Working": true
	},
	"219190":
	{
		"Working": true
	},
	"219200":
	{
		"Working": true
	},
	"219680":
	{
		"Working": true
	},
	"219740":
	{
		"Working": true
	},
	"219830":
	{
		"Working": true
	},
	"220090":
	{
		"Working": true
	},
	"220200":
	{
		"Working": true
	},
	"220460":
	{
		"Working": true
	},
	"220780":
	{
		"Working": true
	},
	"220900":
	{
		"Working": true
	},
	"221020":
	{
		"Working": true
	},
	"221260":
	{
		"Working": true
	},
	"221640":
	{
		"Working": true
	},
	"221810":
	{
		"Working": true
	},
	"221830":
	{
		"Working": true
	},
	"222140":
	{
		"Working": true
	},
	"222260":
	{
		"Hidden": true,
		"Comment": "Europa Universalis IV Beta"
	},
	"222520":
	{
		"Working": true
	},
	"222730":
	{
		"Working": true
	},
	"222750":
	{
		"Working": true
	},
	"223470":
	{
		"Working": true
	},
	"223530":
	{
		"Working": true
	},
	"224260":
	{
		"Working": true
	},
	"224480":
	{
		"Working": true
	},
	"224680":
	{
		"Hidden": true,
		"Comment": "Strike Suit Zero Beta"
	},
	"224760":
	{
		"Working": true
	},
	"224860":
	{
		"Working": true
	},
	"225140":
	{
		"Working": true
	},
	"225160":
	{
		"Working": true
	},
	"225260":
	{
		"Working": true
	},
	"225420":
	{
		"Working": true
	},
	"226600":
	{
		"Hidden": true,
		"Comment": "Octodad: Dadliest Catch Beta"
	},
	"226620":
	{
		"Working": true
	},
	"226960":
	{
		"Working": true
	},
	"227160":
	{
		"Working": true
	},
	"227200":
	{
		"Working": true
	},
	"227300":
	{
		"Working": true
	},
	"227580":
	{
		"Working": true
	},
	"227860":
	{
		"Working": true
	},
	"228440":
	{
		"Working": true
	},
	"228960":
	{
		"Working": true
	},
	"229520":
	{
		"Working": true
	},
	"229680":
	{
		"Hidden": true,
		"Comment": "Guns of Icarus Dev App"
	},
	"230190":
	{
		"Working": true
	},
	"230310":
	{
		"Working": true
	},
	"230760":
	{
		"Working": true
	},
	"231040":
	{
		"Working": true
	},
	"231160":
	{
		"Working": true
	},
	"231200":
	{
		"Working": true
	},
	"231310":
	{
		"Working": true
	},
	"231330":
	{
		"Working": true
	},
	"231670":
	{
		"Working": true
	},
	"231720":
	{
		"Working": true
	},
	"231740":
	{
		"Working": true
	},
	"231910":
	{
		"Working": true
	},
	"232290":
	{
		"Hidden": true,
		"Comment": "Server, not a game."
	},
	"232330":
	{
		"Hidden": true,
		"Comment": "Server, not a game."
	},
	"232370":
	{
		"Hidden": true,
		"Comment": "Server, not a game."
	},
	"232430":
	{
		"Working": true
	},
	"232770":
	{
		"Working": true
	},
	"232790":
	{
		"Working": true
	},
	"233150":
	{
		"Working": true
	},
	"233230":
	{
		"Working": true
	},
	"233250":
	{
		"Working": true
	},
	"233370":
	{
		"Working": true
	},
	"233450":
	{
		"Working": true
	},
	"233720":
	{
		"Working": true
	},
	"233740":
	{
		"Working": true
	},
	"234000":
	{
		"Working": true
	},
	"234060":
	{
		"Working": true
	},
	"234190":
	{
		"Working": true
	},
	"234390":
	{
		"Working": true
	},
	"234650":
	{
		"Working": true
	},
	"234900":
	{
		"Working": true
	},
	"234940":
	{
		"Working": true
	},
	"235820":
	{
		"Working": true
	},
	"235980":
	{
		"Working": true
	},
	"236090":
	{
		"Working": true
	},
	"236170":
	{
		"Hidden": true,
		"Comment": "Server, not a game."
	},
	"236190":
	{
		"Hidden": true,
		"Comment": "Server, not a game."
	},
	"236210":
	{
		"Hidden": true,
		"Comment": "Server, not a game."
	},
	"236730":
	{
		"Working": true
	},
	"236850":
	{
		"Working": true
	},
	"237430":
	{
		"Working": true
	},
	"237470":
	{
		"Working": true
	},
	"237550":
	{
		"Working": true
	},
	"237870":
	{
		"Working": true
	},
	"238210":
	{
		"Working": true
	},
	"238280":
	{
		"Working": true
	},
	"238460":
	{
		"Working": true
	},
	"238690":
	{
		"Hidden": true,
		"Comment": "Server, not a game."
	},
	"238910":
	{
		"Working": true
	},
	"239030":
	{
		"Working": true
	},
	"239070":
	{
		"Working": true
	},
	"239200":
	{
		"Working": true
	},
	"239700":
	{
		"Working": true
	},
	"239820":
	{
		"Working": true
	},
	"240760":
	{
		"Working": true
	},
	"241320":
	{
		"Working": true
	},
	"241600":
	{
		"Working": true
	},
	"241640":
	{
		"Working": true
	},
	"242110":
	{
		"Working": true
	},
	"242360":
	{
		"Hidden": true,
		"Comment": "This is Korean version of Football Manager 2014"
	},
	"242500":
	{
		"Hidden": true,
		"Comment": "Europa Universalis IV Review"
	},
	"242530":
	{
		"Working": true
	},
	"242570":
	{
		"Working": true
	},
	"242680":
	{
		"Working": true
	},
	"242820":
	{
		"Working": true
	},
	"242860":
	{
		"Working": true
	},
	"242880":
	{
		"Working": true
	},
	"243140":
	{
		"Working": true
	},
	"243280":
	{
		"Working": true
	},
	"243780":
	{
		"Working": true
	},
	"244810":
	{
		"Working": true
	},
	"244870":
	{
		"Working": true
	},
	"245150":
	{
		"Working": true
	},
	"245390":
	{
		"Working": true
	},
	"245410":
	{
		"Working": true
	},
	"245430":
	{
		"Working": true
	},
	"245470":
	{
		"Working": true
	},
	"245550":
	{
		"Working": true,
		"Comment": "Overlay doesn't work."
	},
	"246070":
	{
		"Working": true
	},
	"246090":
	{
		"Working": true
	},
	"246360":
	{
		"Working": true
	},
	"246400":
	{
		"Working": true
	},
	"246420":
	{
		"Working": true
	},
	"246680":
	{
		"Working": true
	},
	"246800":
	{
		"Working": true
	},
	"247020":
	{
		"Working": true
	},
	"247870":
	{
		"Working": true
	},
	"248190":
	{
		"Working": true,
		"Comment": "There might be some input glitches on the steam overlay."
	},
	"248410":
	{
		"Working": true
	},
	"248450":
	{
		"Working": true
	},
	"248470":
	{
		"Working": true
	},
	"248510":
	{
		"Working": true
	},
	"248550":
	{
		"Working": true
	},
	"248570":
	{
		"Working": true
	},
	"248610":
	{
		"Working": true
	},
	"248710":
	{
		"Working": true
	},
	"248800":
	{
		"Working": true,
		"Comment": "Need to disable Steamworks on 64bit systems due to a bug.",
		"CommentURL": "http://steamcommunity.com/app/248800/discussions/0/846965705285069220/#c846966336102411647"
	},
	"248860":
	{
		"Working": true,
		"Comment": "Broken overlay."
	},
	"249150":
	{
		"Hidden": true,
		"Comment": "Demo, not a game."
	},
	"249570":
	{
		"Working": true
	},
	"249590":
	{
		"Working": true
	},
	"249630":
	{
		"Working": true
	},
	"249990":
	{
		"Working": true
	},
	"250050":
	{
		"Working": true
	},
	"250110":
	{
		"Working": true
	},
	"250260":
	{
		"Working": true
	},
	"250380":
	{
		"Working": true
	},
	"250420":
	{
		"Working": true,
		"Comment": "Overlay works in server-select window, but not in game window."
	},
	"250460":
	{
		"Working": true
	},
	"250580":
	{
		"Working": true
	},
	"250600":
	{
		"Working": true
	},
	"250620":
	{
		"Working": true
	},
	"251210":
	{
		"Working": true
	},
	"251370":
	{
		"Working": true
	},
	"251410":
	{
		"Working": true
	},
	"251470":
	{
		"Working": true
	},
	"251530":
	{
		"Working": true
	},
	"251630":
	{
		"Working": true
	},
	"251910":
	{
		"Working": true
	},
	"251990":
	{
		"Working": true
	},
	"252010":
	{
		"Working": true,
		"Comment": "The game is not a Linux port but a WINE self contained package."
	},
	"252170":
	{
		"Working": true
	},
	"252250":
	{
		"Working": true
	},
	"252310":
	{
		"Working": true
	},
	"252370":
	{
		"Working": true
	},
	"252410":
	{
		"Working": true
	},
	"252490":
	{
		"Working": true
	},
	"252630":
	{
		"Working": true
	},
	"252670":
	{
		"Working": true
	},
	"252750":
	{
		"Working": true
	},
	"253030":
	{
		"Working": true
	},
	"253110":
	{
		"Working": true,
		"Comment": "Broken overlay."
	},
	"253310":
	{
		"Working": true
	},
	"253410":
	{
		"Working": true
	},
	"253570":
	{
		"Working": true
	},
	"253650":
	{
		"Working": true
	},
	"253790":
	{
		"Working": true
	},
	"255300":
	{
		"Working": true
	},
	"255340":
	{
		"Working": true
	},
	"255870":
	{
		"Working": true
	},
	"255920":
	{
		"Working": true
	},
	"257120":
	{
		"Working": true
	},
	"257670":
	{
		"Working": true
	},
	"257770":
	{
		"Working": true
	},
	"257830":
	{
		"Working": true
	},
	"257870":
	{
		"Working": true
	},
	"257930":
	{
		"Working": true
	},
	"258050":
	{
		"Working": true
	},
	"258550":
	{
		"Hidden": true,
		"Comment": "Server, not a game."
	},
	"258890":
	{
		"Working": true
	},
	"258950":
	{
		"Working": true
	},
	"259060":
	{
		"Working": true
	},
	"259130":
	{
		"Working": true
	},
	"259390":
	{
		"Working": true
	},
	"259430":
	{
		"Working": true
	},
	"259450":
	{
		"Working": true
	},
	"259470":
	{
		"Working": true
	},
	"259510":
	{
		"Working": true
	},
	"259530":
	{
		"Working": true
	},
	"259600":
	{
		"Working": true
	},
	"259620":
	{
		"Working": true
	},
	"259680":
	{
		"Working": true
	},
	"259700":
	{
		"Working": true
	},
	"259720":
	{
		"Working": true
	},
	"259740":
	{
		"Working": true
	},
	"259780":
	{
		"Working": true
	},
	"260790":
	{
		"Working": true,
		"Comment": "Steam Overlay broken with 64-bit version."
	},
	"261350":
	{
		"Working": true
	},
	"261680":
	{
		"Working": true
	},
	"261700":
	{
		"Working": true
	},
	"261820":
	{
		"Working": true
	},
	"261960":
	{
		"Working": true
	},
	"262260":
	{
		"Working": true
	},
	"262690":
	{
		"Working": true
	},
	"262940":
	{
		"Working": true
	},
	"263320":
	{
		"Working": true
	},
	"263340":
	{
		"Working": true
	},
	"263360":
	{
		"Working": true
	},
	"263420":
	{
		"Working": true
	},
	"263460":
	{
		"Working": true
	},
	"264060":
	{
		"Working": true
	},
	"264080":
	{
		"Working": true
	},
	"264140":
	{
		"Working": true,
		"Beta": true
	},
	"264160":
	{
		"Working": true
	},
	"264280":
	{
		"Working": true
	},
	"264340":
	{
		"Working": true
	},
	"264380":
	{
		"Working": true
	},
	"264730":
	{
		"Working": true,
		"Comment": "Broken overlay."
	},
	"265380":
	{
		"Working": true
	},
	"265630":
	{
		"Working": true
	},
	"265670":
	{
		"Working": true
	},
	"265770":
	{
		"Working": true
	},
	"265830":
	{
		"Working": true
	},
	"265890":
	{
		"Working": true
	},
	"266010":
	{
		"Working": true
	},
	"266090":
	{
		"Working": true
	},
	"266130":
	{
		"Working": true
	},
	"267060":
	{
		"Working": true
	},
	"267670":
	{
		"Working": true
	},
	"268810":
	{
		"Working": true
	},
	"269150":
	{
		"Working": true
	},
	"269810":
	{
		"Working": true
	},
	"270150":
	{
		"Working": true
	},
	"270330":
	{
		"Working": true
	},
	"270450":
	{
		"Working": true
	},
	"270750":
	{
		"Working": true
	},
	"270760":
	{
		"Working": true
	},
	"271820":
	{
		"Working": true
	},
	"271900":
	{
		"Working": true
	},
	"272060":
	{
		"Working": true
	},
	"273070":
	{
		"Working": true
	},
	"274450":
	{
		"Working": true
	},
	"279160":
	{
		"Working": true
	},
	"280220":
	{
		"Working": true
	},
	"280910":
	{
		"Working": true
	},
	"282760":
	{
		"Working": true
	},
	"282880":
	{
		"Working": true
	},
	"283040":
	{
		"Working": true
	},
	"283270":
	{
		"Working": true
	},
	"283980":
	{
		"Working": true
	},
	"284710":
	{
		"Working": true
	},
	"286100":
	{
		"Working": true,
		"Comment": "This game has only 64-bit binaries."
	},
	"286380":
	{
		"Working": true
	},
	"287020":
	{
		"Working": true
	},
	"287580":
	{
		"Working": true,
		"Comment": "Partly broken overlay (does not accept input)"
	},
	"290060":
	{
		"Working": true
	},
	"290280":
	{
		"Working": true
	},
	"290770":
	{
		"Working": true
	},
	"291030":
	{
		"Working": true
	},
	"291050":
	{
		"Working": true
	},
	"291430":
	{
		"Working": true
	},
	"293200":
	{
		"Working": true
	},
	"293300":
	{
		"Working": true
	},
	"293860":
	{
		"Working": true
	},
	"294230":
	{
		"Working": true
	},
	"295610":
	{
		"Working": true
	},
	"296850":
	{
		"Working": true
	},
	"297120":
	{
		"Working": true,
		"Comment": "Flickering graphics during menus on AMD fglrx drivers"
	},
	"299780":
	{
		"Working": true
	},
	"301190":
	{
		"Working": true
	},
	"301360":
	{
		"Working": true,
		"Comment": "This game has only 64-bit binaries."
	}
}
